jbqt/__init__.py
jbqt/common/__init__.py
jbqt/common/qt_utils.py
jbqt/consts/__init__.py
jbqt/dialogs/__init__.py
jbqt/dialogs/file_dialog.py
jbqt/dialogs/input_form.py
jbqt/dialogs/single_input.py
jbqt/dialogs/text_preview.py
jbqt/models/__init__.py
jbqt/models/chip_button.py
jbqt/models/chips.py
jbqt/models/dialog_options.py
jbqt/models/model_consts.py
jbqt/models/model_utils.py
jbqt/models/toolbar_button.py
jbqt/types/__init__.py
jbqt/view_icons.py
jbqt/widgets/__init__.py
jbqt/widgets/chip_button.py
jbqt/widgets/chips.py
jbqt/widgets/multiselect.py
jbqt/widgets/simple.py
jbqt/widgets/toast.py
jbqt/widgets/widget_utils.py
jbqt-0.1.30.dist-info/METADATA
jbqt-0.1.30.dist-info/WHEEL
jbqt-0.1.30.dist-info/RECORD
