Metadata-Version: 2.1
Name: jbqt
Version: 0.1.30
Summary: 
Author: Joseph Bochinski
Author-email: stirgejr@gmail.com
Requires-Python: >=3.12,<4.0
Classifier: Programming Language :: Python :: 3
Classifier: Programming Language :: Python :: 3.12
Requires-Dist: fuzzywuzzy (>=0.18.0,<0.19.0)
Requires-Dist: jbconsts (>=0.1.1,<0.2.0)
Requires-Dist: jbutils (>=0.2.2,<0.3.0)
Requires-Dist: pyqt6 (>=6.9.0,<7.0.0)
Requires-Dist: python-levenshtein (>=0.27.1,<0.28.0)
Requires-Dist: rich (>=14.0.0,<15.0.0)
